musicpd.py
debug/fetch.py
debug/fetch_albumart.py
debug/fetch_readpicture.py
debug/readpicture.py
python_musicpd-0.9.2.dist-info/licenses/LICENSE.txt
python_musicpd-0.9.2.dist-info/METADATA
python_musicpd-0.9.2.dist-info/WHEEL
python_musicpd-0.9.2.dist-info/top_level.txt
python_musicpd-0.9.2.dist-info/RECORD
