Metadata-Version: 2.4
Name: python-musicpd
Version: 0.9.2
Summary: An MPD (Music Player Daemon) client library written in pure Python.
Author-email: Kaliko Jack <kaliko@azylum.org>
License-Expression: LGPL-3.0-or-later
Project-URL: Homepage, https://kaliko.me/python-musicpd/
Keywords: mpd,Music Player Daemon
Classifier: Development Status :: 5 - Production/Stable
Classifier: Intended Audience :: Developers
Classifier: Natural Language :: English
Classifier: Operating System :: OS Independent
Classifier: Programming Language :: Python :: 3
Classifier: Topic :: Software Development :: Libraries :: Python Modules
Requires-Python: >=3.6
License-File: LICENSE.txt
Provides-Extra: sphinx
Requires-Dist: Sphinx>=5.3.0; extra == "sphinx"
Dynamic: license-file
